ThiagoPy/__init__.py
ThiagoPy/microstates.jl
ThiagoPy/microstates.py
ThiagoPy-0.5.dist-info/METADATA
ThiagoPy-0.5.dist-info/WHEEL
ThiagoPy-0.5.dist-info/top_level.txt
ThiagoPy-0.5.dist-info/RECORD
