Metadata-Version: 2.1
Name: ThiagoPy
Version: 0.5
Summary: Uma biblioteca Python que usa funções Julia
Home-page: UNKNOWN
Author: Jorge Vinicius Malosti da Silveira
Author-email: jorge.malosti@outlook.com
License: UNKNOWN
Platform: UNKNOWN
Classifier: Programming Language :: Python :: 3
Classifier: License :: OSI Approved :: MIT License
Classifier: Operating System :: OS Independent
Requires-Python: >=3.6
Requires-Dist: julia
